LICENSE
MANIFEST.in
README.rst
setup.py
Pyxolotl.egg-info/PKG-INFO
Pyxolotl.egg-info/SOURCES.txt
Pyxolotl.egg-info/dependency_links.txt
Pyxolotl.egg-info/entry_points.txt
Pyxolotl.egg-info/requires.txt
Pyxolotl.egg-info/top_level.txt
pyxolotl/__init__.py
pyxolotl/__main__.py
pyxolotl/config.py
pyxolotl/core.py
pyxolotl/cryptostorage.py
pyxolotl/exceptions.py
pyxolotl/version.py
pyxolotl/encoder/__init__.py
pyxolotl/encoder/base64.py
pyxolotl/encoder/mnemonic.py
pyxolotl/protocol/__init__.py
pyxolotl/protocol/basic.py
pyxolotl/store/__init__.py
pyxolotl/store/sqlite/__init__.py
pyxolotl/store/sqlite/liteaxolotlstore.py
pyxolotl/store/sqlite/liteidentitykeystore.py
pyxolotl/store/sqlite/liteprekeystore.py
pyxolotl/store/sqlite/litesessionstore.py
pyxolotl/store/sqlite/litesignedprekeystore.py
pyxolotl/transport/__init__.py
pyxolotl/transport/email.py
pyxolotl/transport/plaintext.py