Metadata-Version: 1.1
Name: Pyxolotl
Version: 0.2
Summary: Send and receive messages encrypted with Axolotl (Double Ratchet) protocol
Home-page: https://github.com/xmikos/pyxolotl
Author: Michal Krenek (Mikos)
Author-email: m.krenek@gmail.com
License: GNU GPLv3
Platform: UNKNOWN
Classifier: Development Status :: 4 - Beta
Classifier: Environment :: Console
Classifier: Intended Audience :: End Users/Desktop
Classifier: License :: OSI Approved :: GNU General Public License v3 or later (GPLv3+)
Classifier: Natural Language :: English
Classifier: Operating System :: OS Independent
Classifier: Programming Language :: Python :: 3
Classifier: Programming Language :: Python :: 3.3
Classifier: Programming Language :: Python :: 3.4
Classifier: Programming Language :: Python :: 3.5
Classifier: Topic :: Communications :: Chat
Classifier: Topic :: Security :: Cryptography
